drive_flow/__init__.py
drive_flow/broker.py
drive_flow/core.py
drive_flow/dynamic.py
drive_flow/types.py
drive_flow/utils.py
drive_flow-0.0.1.dist-info/LICENSE
drive_flow-0.0.1.dist-info/METADATA
drive_flow-0.0.1.dist-info/WHEEL
drive_flow-0.0.1.dist-info/top_level.txt
drive_flow-0.0.1.dist-info/RECORD
